LICENSE
opentelemetry_instrumentation_django_stomp/__init__.py
opentelemetry_instrumentation_django_stomp/instrumentors/__init__.py
opentelemetry_instrumentation_django_stomp/instrumentors/consumer_instrument.py
opentelemetry_instrumentation_django_stomp/instrumentors/publisher_instrument.py
opentelemetry_instrumentation_django_stomp/package.py
opentelemetry_instrumentation_django_stomp/utils/__init__.py
opentelemetry_instrumentation_django_stomp/utils/django_stomp_getter.py
opentelemetry_instrumentation_django_stomp/utils/shared_types.py
opentelemetry_instrumentation_django_stomp/utils/span.py
opentelemetry_instrumentation_django_stomp/utils/traced_thread_pool_executor.py
opentelemetry_instrumentation_django_stomp/version.py
opentelemetry_instrumentation_django_stomp-0.4.0.dist-info/LICENSE
opentelemetry_instrumentation_django_stomp-0.4.0.dist-info/METADATA
opentelemetry_instrumentation_django_stomp-0.4.0.dist-info/WHEEL
opentelemetry_instrumentation_django_stomp-0.4.0.dist-info/RECORD
