Metadata-Version: 2.1
Name: opentelemetry-instrumentation-django-stomp
Version: 0.4.0
Summary: Opentelemetry instrumentor for django-stomp package
Home-page: https://github.com/juntossomosmais/opentelemetry-instrumentation-django-stomp
License: MIT
Keywords: django-stomp,stomp,django,opentelemetry,instrumentation
Author: Juntos Somos Mais
Author-email: labs@juntossomosmais.com.br
Requires-Python: >=3.10,<4.0
Classifier: License :: OSI Approved :: MIT License
Classifier: Programming Language :: Python :: 3
Classifier: Programming Language :: Python :: 3.10
Classifier: Programming Language :: Python :: 3.11
Requires-Dist: Django
Requires-Dist: django-stomp (>=6.0.0,<7.0.0)
Requires-Dist: opentelemetry-api
Requires-Dist: opentelemetry-instrumentation
Requires-Dist: opentelemetry-sdk
Project-URL: Repository, https://github.com/juntossomosmais/opentelemetry-instrumentation-django-stomp
